MANIFEST.in
README.md
requirements.txt
setup.cfg
setup.py
coform/__init__.py
coform.egg-info/PKG-INFO
coform.egg-info/SOURCES.txt
coform.egg-info/dependency_links.txt
coform.egg-info/requires.txt
coform.egg-info/top_level.txt