Metadata-Version: 1.1
Name: coform
Version: 0.0.2
Summary: A thin form handling library written around colander.
Home-page: https://github.com/mmerickel/coform
Author: Michael Merickel
Author-email: michael@merickel.org
License: BSD
Download-URL: https://github.com/mmerickel/coform/tarball/0.0.2
Platform: UNKNOWN
Classifier: Development Status :: 3 - Alpha
Classifier: Intended Audience :: Developers
Classifier: Programming Language :: Python :: 3
